ffmirror/__init__.py
ffmirror/cli.py
ffmirror/core.py
ffmirror/handlers/__init__.py
ffmirror/handlers/ao3.py
ffmirror/handlers/ffnet.py
ffmirror/metadb.py
ffmirror/mirror.py
ffmirror/simpletags.py
ffmirror/util.py
ffmirror-0.4.1.dist-info/entry_points.txt
ffmirror-0.4.1.dist-info/WHEEL
ffmirror-0.4.1.dist-info/METADATA
ffmirror-0.4.1.dist-info/RECORD
