Metadata-Version: 2.1
Name: ffmirror
Version: 0.4.1
Summary: Local mirror for Internet fiction sites
Home-page: https://github.com/alethiophile/ffmirror
License: MIT
Author: alethiophile
Author-email: tomdicksonhunt@gmail.com
Requires-Python: >=3.7,<4.0
Classifier: License :: OSI Approved :: MIT License
Classifier: Programming Language :: Python :: 3
Classifier: Programming Language :: Python :: 3.10
Classifier: Programming Language :: Python :: 3.7
Classifier: Programming Language :: Python :: 3.8
Classifier: Programming Language :: Python :: 3.9
Requires-Dist: SQLAlchemy (>=1.4.42,<2.0.0)
Requires-Dist: attrs (>=19.3,<20.0)
Requires-Dist: beautifulsoup4 (>=4.7,<5.0)
Requires-Dist: click (>=8.1.3,<9.0.0)
Requires-Dist: cloudscraper (>=1.2.50,<2.0.0)
Requires-Dist: html2text (>=2019.9,<2020.0)
Requires-Dist: html5lib (>=1.0,<2.0)
Requires-Dist: python-dateutil (>=2.7,<3.0)
Requires-Dist: requests (>=2.22,<3.0)
Project-URL: Repository, https://github.com/alethiophile/ffmirror
